julia/__init__.py
julia/api.py
julia/compile.jl
julia/core.py
julia/find_libpython.py
julia/install-packagecompiler.jl
julia/install.jl
julia/julia_py.py
julia/juliainfo.jl
julia/juliainfo.py
julia/libjulia.py
julia/magic.py
julia/options.py
julia/patch.jl
julia/precompile.jl
julia/pseudo_python_cli.py
julia/pyjulia_helper.jl
julia/pytestplugin.py
julia/python_jl.py
julia/release.py
julia/runtests.py
julia/sysimage.py
julia/tools.py
julia/utils.py
julia/with_rebuilt.py
julia/ipy/__init__.py
julia/ipy/monkeypatch_completer.py
julia/ipy/monkeypatch_interactiveshell.py
julia/ipy/revise.py
julia/tests/__init__.py
julia/tests/conftest.py
julia/tests/test_compatible_exe.py
julia/tests/test_core.py
julia/tests/test_find_libpython.py
julia/tests/test_install.py
julia/tests/test_juliainfo.py
julia/tests/test_juliaoptions.py
julia/tests/test_libjulia.py
julia/tests/test_magic.py
julia/tests/test_options.py
julia/tests/test_plugin.py
julia/tests/test_pseudo_python_cli.py
julia/tests/test_python_jl.py
julia/tests/test_runtests.py
julia/tests/test_sysimage.py
julia/tests/test_tools.py
julia/tests/test_utils.py
julia/tests/utils.py
julia-0.6.2.dist-info/LICENSE.md
julia-0.6.2.dist-info/METADATA
julia-0.6.2.dist-info/WHEEL
julia-0.6.2.dist-info/entry_points.txt
julia-0.6.2.dist-info/top_level.txt
julia-0.6.2.dist-info/RECORD
