Metadata-Version: 2.1
Name: julia
Version: 0.6.2
Summary: Julia/Python bridge with IPython support.
Home-page: http://julialang.org
Author: The Julia and IPython development teams.
Author-email: julia@julialang.org
License: MIT
Project-URL: Source, https://github.com/JuliaPy/pyjulia
Project-URL: Tracker, https://github.com/JuliaPy/pyjulia/issues
Project-URL: Documentation, https://pyjulia.readthedocs.io
Keywords: julia python
Platform: UNKNOWN
Classifier: Development Status :: 3 - Alpha
Classifier: License :: OSI Approved :: MIT License
Classifier: Programming Language :: Python :: 3
Classifier: Programming Language :: Python :: 3.4
Classifier: Programming Language :: Python :: 3.5
Classifier: Programming Language :: Python :: 3.6
Classifier: Programming Language :: Python :: 3.7
Classifier: Programming Language :: Python :: 3.8
Classifier: Programming Language :: Python :: 3.9
Classifier: Programming Language :: Python :: 3.10
Classifier: Programming Language :: Python :: 3.11
Classifier: Programming Language :: Python :: 3.12
Requires-Python: >=3.4
Provides-Extra: test
License-File: LICENSE.md
